omnata_cli/__init__.py
omnata_cli-0.2.3.dist-info/METADATA
omnata_cli-0.2.3.dist-info/WHEEL
omnata_cli-0.2.3.dist-info/entry_points.txt
omnata_cli-0.2.3.dist-info/licenses/LICENSE
omnata_cli-0.2.3.dist-info/RECORD
