Metadata-Version: 2.4
Name: omnata-cli
Version: 0.2.3
Summary: A command line interface for Omnata
License-File: LICENSE
Author: James Weakley
Author-email: james.weakley@omnata.com
Requires-Python: >=3.10,<4.0
Classifier: Programming Language :: Python :: 3
Classifier: Programming Language :: Python :: 3.10
Classifier: Programming Language :: Python :: 3.11
Classifier: Programming Language :: Python :: 3.12
Classifier: Programming Language :: Python :: 3.13
Classifier: Programming Language :: Python :: 3.14
Requires-Dist: click (<=8.2.1)
Requires-Dist: typer (>=0.9,<0.10)
